.DS_Store
woqlclient/__init__.py
woqlclient/__version__.py
woqlclient/connectionCapabilities.py
woqlclient/connectionConfig.py
woqlclient/const.py
woqlclient/dispatchRequest.py
woqlclient/documentTemplate.py
woqlclient/errorMessage.py
woqlclient/errors.py
woqlclient/idParser.py
woqlclient/utils.py
woqlclient/woql.py
woqlclient/woqlClient.py
terminus_client_python-0.0.4.dist-info/LICENSE
terminus_client_python-0.0.4.dist-info/METADATA
terminus_client_python-0.0.4.dist-info/WHEEL
terminus_client_python-0.0.4.dist-info/top_level.txt
terminus_client_python-0.0.4.dist-info/RECORD
