Metadata-Version: 2.1
Name: terminus-client-python
Version: 0.0.4
Summary: Python client for Terminus DB
Home-page: https://github.com/terminusdb/terminus-client-python
Author: TerminusDB group
Author-email: terminusdatabase@gmail.com
License: UNKNOWN
Platform: UNKNOWN
Classifier: Programming Language :: Python :: 3
Classifier: License :: OSI Approved :: GNU General Public License v3 (GPLv3)
Classifier: Operating System :: OS Independent
Requires-Python: >=3.6
Requires-Dist: requests
